shieldix/__init__.py
shieldix/bytecode/__init__.py
shieldix/bytecode/bc1.py
shieldix/bytecode/bc10.py
shieldix/bytecode/bc11.py
shieldix/bytecode/bc12.py
shieldix/bytecode/bc13.py
shieldix/bytecode/bc14.py
shieldix/bytecode/bc15.py
shieldix/bytecode/bc16.py
shieldix/bytecode/bc17.py
shieldix/bytecode/bc18.py
shieldix/bytecode/bc19.py
shieldix/bytecode/bc2.py
shieldix/bytecode/bc20.py
shieldix/bytecode/bc21.py
shieldix/bytecode/bc22.py
shieldix/bytecode/bc23.py
shieldix/bytecode/bc24.py
shieldix/bytecode/bc25.py
shieldix/bytecode/bc26.py
shieldix/bytecode/bc27.py
shieldix/bytecode/bc28.py
shieldix/bytecode/bc29.py
shieldix/bytecode/bc3.py
shieldix/bytecode/bc30.py
shieldix/bytecode/bc4.py
shieldix/bytecode/bc5.py
shieldix/bytecode/bc6.py
shieldix/bytecode/bc7.py
shieldix/bytecode/bc8.py
shieldix/bytecode/bc9.py
shieldix/bytecode/bytecode_compiler.py
shieldix/core/__init__.py
shieldix/core/crp34.py
shieldix/core/enc33.py
shieldix/core/encryption_engine.py
shieldix/core/layer1_transform.py
shieldix/core/lyr10.py
shieldix/core/lyr11.py
shieldix/core/lyr12.py
shieldix/core/lyr13.py
shieldix/core/lyr14.py
shieldix/core/lyr15.py
shieldix/core/lyr16.py
shieldix/core/lyr17.py
shieldix/core/lyr18.py
shieldix/core/lyr19.py
shieldix/core/lyr2.py
shieldix/core/lyr20.py
shieldix/core/lyr21.py
shieldix/core/lyr22.py
shieldix/core/lyr23.py
shieldix/core/lyr24.py
shieldix/core/lyr25.py
shieldix/core/lyr26.py
shieldix/core/lyr27.py
shieldix/core/lyr28.py
shieldix/core/lyr29.py
shieldix/core/lyr3.py
shieldix/core/lyr30.py
shieldix/core/lyr4.py
shieldix/core/lyr5.py
shieldix/core/lyr6.py
shieldix/core/lyr7.py
shieldix/core/lyr8.py
shieldix/core/lyr9.py
shieldix/core/phx31.py
shieldix/core/sec35.py
shieldix/core/sec36.py
shieldix/core/sec37.py
shieldix/core/sec38.py
shieldix/core/sec39.py
shieldix/core/sec40.py
shieldix/core/xor32.py
shieldix/executor/__init__.py
shieldix/executor/ex1.py
shieldix/executor/ex10.py
shieldix/executor/ex11.py
shieldix/executor/ex12.py
shieldix-0.1.0.dist-info/LICENSE
shieldix-0.1.0.dist-info/METADATA
shieldix-0.1.0.dist-info/WHEEL
shieldix-0.1.0.dist-info/top_level.txt
shieldix-0.1.0.dist-info/RECORD
