Metadata-Version: 2.1
Name: shieldix
Version: 0.1.0
Summary: A standalone Python library with no external dependencies
Home-page: https://github.com/MERO/shieldix
Author: MERO
Author-email: contact@shieldix.dev
License: MIT
Project-URL: Homepage, https://t.me/QP4RM
Project-URL: Issues, https://t.me/QP4RM
Keywords: shield,security,protection,standalone
Requires-Python: >=2.7
License-File: LICENSE
Provides-Extra: dev
Requires-Dist: pytest>=7.4.3; extra == "dev"
Requires-Dist: black>=23.12.0; extra == "dev"
Requires-Dist: flake8>=6.1.0; extra == "dev"
